pci/PCI_App.py
pci/__init__.py
pci/enodebfunction.py
pci-0.2.3.dist-info/LICENSE.txt
pci-0.2.3.dist-info/METADATA
pci-0.2.3.dist-info/WHEEL
pci-0.2.3.dist-info/dependency_links.txt
pci-0.2.3.dist-info/top_level.txt
pci-0.2.3.dist-info/RECORD
