Metadata-Version: 2.1
Name: pci
Version: 0.2.3
Summary: PCI group estimate
Home-page: https://testpypi.python.org/pypi/pci
Author: zhongj
Author-email: zhong_jie@foxmail.com
License: LICENSE.txt
Platform: UNKNOWN
Classifier: Programming Language :: Python :: 3
Classifier: License :: OSI Approved :: MIT License
Classifier: Operating System :: OS Independent
Requires-Python: >=3.5
Requires-Dist: pandas (>=0.23.4)
Requires-Dist: numpy (>=1.16.3)
Requires-Dist: folium (==0.10.1)
Requires-Dist: geopy (==1.20.0)
